nbdev_squ/__init__.py
wagov_squ/__init__.py
wagov_squ/api.py
wagov_squ/atlaskit-transformer.bundle.js
wagov_squ/context.py
wagov_squ/core.py
wagov_squ/exceptions.py
wagov_squ/frame.py
wagov_squ/legacy.py
wagov_squ/settings.py
wagov_squ-1.5.3.dist-info/licenses/LICENSE
wagov_squ-1.5.3.dist-info/METADATA
wagov_squ-1.5.3.dist-info/WHEEL
wagov_squ-1.5.3.dist-info/top_level.txt
wagov_squ-1.5.3.dist-info/RECORD
