Metadata-Version: 2.4
Name: wagov-squ
Version: 1.5.3
Summary: Python SIEM Query Utils with Ibis support
Author-email: Adon Metcalfe <adonm@fastmail.fm>
License-Expression: Apache-2.0
Project-URL: Homepage, https://github.com/wagov/nbdev-squ
Project-URL: Documentation, https://wagov.github.io/nbdev-squ
Project-URL: Repository, https://github.com/wagov/nbdev-squ
Project-URL: Issues, https://github.com/wagov/nbdev-squ/issues
Keywords: siem,security,azure,sentinel,query,automation
Classifier: Development Status :: 4 - Beta
Classifier: Intended Audience :: Developers
Classifier: Programming Language :: Python :: 3
Classifier: Programming Language :: Python :: 3.12
Classifier: Programming Language :: Python :: 3.13
Requires-Python: >=3.12
License-File: LICENSE
Requires-Dist: tenacity
Requires-Dist: platformdirs
Requires-Dist: universal-pathlib
Requires-Dist: adlfs
Requires-Dist: diskcache
Requires-Dist: azure-cli>=2.77
Requires-Dist: azure-monitor-query
Requires-Dist: azure-kusto-data
Requires-Dist: atlassian-python-api
Requires-Dist: abuseipdb-wrapper
Requires-Dist: pysigma
Requires-Dist: pandas
Requires-Dist: dbt-duckdb
Requires-Dist: python-benedict
Requires-Dist: markdown
Requires-Dist: pytenable
Requires-Dist: httpx
Requires-Dist: msticpy[azsentinel]
Requires-Dist: ibis-framework[duckdb]
Requires-Dist: duckdb
Requires-Dist: pip>=25.2
Requires-Dist: pydantic>=2.0
Requires-Dist: pydantic-settings>=2.0
Requires-Dist: semver>=3.0.4
Requires-Dist: pandas-stubs>=2.3.2.250827
Provides-Extra: dev
Requires-Dist: pytest>=7.0; extra == "dev"
Requires-Dist: pytest-cov; extra == "dev"
Requires-Dist: ruff; extra == "dev"
Requires-Dist: mypy; extra == "dev"
Requires-Dist: pre-commit; extra == "dev"
Dynamic: license-file
